{"episode_rewards": [{"py/reduce": [{"py/function": "numpy.core.multiarray.scalar"}, {"py/tuple": [{"py/reduce": [{"py/type": "numpy.dtype"}, {"py/tuple": ["f8", false, true]}, {"py/tuple": [3, "<", null, null, null, -1, -1, 0]}]}, {"py/b64": "r5gd+C7BEcA="}]}]}, {"py/reduce": [{"py/function": "numpy.core.multiarray.scalar"}, {"py/tuple": [{"py/id": 2}, {"py/b64": "bn7RWuXZFMA="}]}]}, {"py/reduce": [{"py/function": "numpy.core.multiarray.scalar"}, {"py/tuple": [{"py/id": 2}, {"py/b64": "hMV2c4NlE8A="}]}]}, {"py/reduce": [{"py/function": "numpy.core.multiarray.scalar"}, {"py/tuple": [{"py/id": 2}, {"py/b64": "OBm82uW9DMA="}]}]}, {"py/reduce": [{"py/function": "numpy.core.multiarray.scalar"}, {"py/tuple": [{"py/id": 2}, {"py/b64": "HNFNjwT5D8A="}]}]}, {"py/reduce": [{"py/function": "numpy.core.multiarray.scalar"}, {"py/tuple": [{"py/id": 2}, {"py/b64": "b/ovPiWWFcA="}]}]}, {"py/reduce": [{"py/function": "numpy.core.multiarray.scalar"}, {"py/tuple": [{"py/id": 2}, {"py/b64": "OVeqc69mEsA="}]}]}, {"py/reduce": [{"py/function": "numpy.core.multiarray.scalar"}, {"py/tuple": [{"py/id": 2}, {"py/b64": "owaFxuNPDsA="}]}]}, {"py/reduce": [{"py/function": "numpy.core.multiarray.scalar"}, {"py/tuple": [{"py/id": 2}, {"py/b64": "Jn1/V/mcEcA="}]}]}, {"py/reduce": [{"py/function": "numpy.core.multiarray.scalar"}, {"py/tuple": [{"py/id": 2}, {"py/b64": "+t1MliV6DsA="}]}]}, {"py/reduce": [{"py/function": "numpy.core.multiarray.scalar"}, {"py/tuple": [{"py/id": 2}, {"py/b64": "Tl4kGD7YEcA="}]}]}, {"py/reduce": [{"py/function": "numpy.core.multiarray.scalar"}, {"py/tuple": [{"py/id": 2}, {"py/b64": "9LrWTe0TEcA="}]}]}, {"py/reduce": [{"py/function": "numpy.core.multiarray.scalar"}, {"py/tuple": [{"py/id": 2}, {"py/b64": "7F1RQX+rEMA="}]}]}, {"py/reduce": [{"py/function": "numpy.core.multiarray.scalar"}, {"py/tuple": [{"py/id": 2}, {"py/b64": "8/EgJTfxEsA="}]}]}, {"py/reduce": [{"py/function": "numpy.core.multiarray.scalar"}, {"py/tuple": [{"py/id": 2}, {"py/b64": "Kn06J7dSD8A="}]}]}, {"py/reduce": [{"py/function": "numpy.core.multiarray.scalar"}, {"py/tuple": [{"py/id": 2}, {"py/b64": "LbptP2upE8A="}]}]}, {"py/reduce": [{"py/function": "numpy.core.multiarray.scalar"}, {"py/tuple": [{"py/id": 2}, {"py/b64": "ZbtyDIxzDsA="}]}]}, {"py/reduce": [{"py/function": "numpy.core.multiarray.scalar"}, {"py/tuple": [{"py/id": 2}, {"py/b64": "tltsCm05FMA="}]}]}, {"py/reduce": [{"py/function": "numpy.core.multiarray.scalar"}, {"py/tuple": [{"py/id": 2}, {"py/b64": "BRBhAqaXEMA="}]}]}, {"py/reduce": [{"py/function": "numpy.core.multiarray.scalar"}, {"py/tuple": [{"py/id": 2}, {"py/b64": "VoirBRNSEcA="}]}]}, {"py/reduce": [{"py/function": "numpy.core.multiarray.scalar"}, {"py/tuple": [{"py/id": 2}, {"py/b64": "q3o4YhQOE8A="}]}]}, {"py/reduce": [{"py/function": "numpy.core.multiarray.scalar"}, {"py/tuple": [{"py/id": 2}, {"py/b64": "fdp69KQjEcA="}]}]}, {"py/reduce": [{"py/function": "numpy.core.multiarray.scalar"}, {"py/tuple": [{"py/id": 2}, {"py/b64": "tunL8M7hE8A="}]}]}, {"py/reduce": [{"py/function": "numpy.core.multiarray.scalar"}, {"py/tuple": [{"py/id": 2}, {"py/b64": "cOlTjtPxEMA="}]}]}, {"py/reduce": [{"py/function": "numpy.core.multiarray.scalar"}, {"py/tuple": [{"py/id": 2}, {"py/b64": "EaewCeMoDsA="}]}]}, {"py/reduce": [{"py/function": "numpy.core.multiarray.scalar"}, {"py/tuple": [{"py/id": 2}, {"py/b64": "BAP04gMEEcA="}]}]}, {"py/reduce": [{"py/function": "numpy.core.multiarray.scalar"}, {"py/tuple": [{"py/id": 2}, {"py/b64": "Na7Q/hcGEMA="}]}]}, {"py/reduce": [{"py/function": "numpy.core.multiarray.scalar"}, {"py/tuple": [{"py/id": 2}, {"py/b64": "8dgjHwyiEcA="}]}]}, {"py/reduce": [{"py/function": "numpy.core.multiarray.scalar"}, {"py/tuple": [{"py/id": 2}, {"py/b64": "+2SkhZVwE8A="}]}]}, {"py/reduce": [{"py/function": "numpy.core.multiarray.scalar"}, {"py/tuple": [{"py/id": 2}, {"py/b64": "SbyRCxNFEcA="}]}]}, {"py/reduce": [{"py/function": "numpy.core.multiarray.scalar"}, {"py/tuple": [{"py/id": 2}, {"py/b64": "LOzgfSYwDsA="}]}]}, {"py/reduce": [{"py/function": "numpy.core.multiarray.scalar"}, {"py/tuple": [{"py/id": 2}, {"py/b64": "etS5zDEKEcA="}]}]}, {"py/reduce": [{"py/function": "numpy.core.multiarray.scalar"}, {"py/tuple": [{"py/id": 2}, {"py/b64": "5JIxWx8hEsA="}]}]}, {"py/reduce": [{"py/function": "numpy.core.multiarray.scalar"}, {"py/tuple": [{"py/id": 2}, {"py/b64": "qLYQG6EgEsA="}]}]}, {"py/reduce": [{"py/function": "numpy.core.multiarray.scalar"}, {"py/tuple": [{"py/id": 2}, {"py/b64": "6+nSG/GYEcA="}]}]}, {"py/reduce": [{"py/function": "numpy.core.multiarray.scalar"}, {"py/tuple": [{"py/id": 2}, {"py/b64": "Y+pv9ZQvEcA="}]}]}, {"py/reduce": [{"py/function": "numpy.core.multiarray.scalar"}, {"py/tuple": [{"py/id": 2}, {"py/b64": "+1MvfUD/EcA="}]}]}, {"py/reduce": [{"py/function": "numpy.core.multiarray.scalar"}, {"py/tuple": [{"py/id": 2}, {"py/b64": "E7/2Ru3UFcA="}]}]}, {"py/reduce": [{"py/function": "numpy.core.multiarray.scalar"}, {"py/tuple": [{"py/id": 2}, {"py/b64": "2ozZaS1bEcA="}]}]}, {"py/reduce": [{"py/function": "numpy.core.multiarray.scalar"}, {"py/tuple": [{"py/id": 2}, {"py/b64": "KhvTUIKSEcA="}]}]}, {"py/reduce": [{"py/function": "numpy.core.multiarray.scalar"}, {"py/tuple": [{"py/id": 2}, {"py/b64": "5aDONRSPEsA="}]}]}, {"py/reduce": [{"py/function": "numpy.core.multiarray.scalar"}, {"py/tuple": [{"py/id": 2}, {"py/b64": "T3Zv+8LuD8A="}]}]}, {"py/reduce": [{"py/function": "numpy.core.multiarray.scalar"}, {"py/tuple": [{"py/id": 2}, {"py/b64": "AAxZA9cRDcA="}]}]}, {"py/reduce": [{"py/function": "numpy.core.multiarray.scalar"}, {"py/tuple": [{"py/id": 2}, {"py/b64": "ihO8T7BcEsA="}]}]}, {"py/reduce": [{"py/function": "numpy.core.multiarray.scalar"}, {"py/tuple": [{"py/id": 2}, {"py/b64": "SXgJTCjbEsA="}]}]}, {"py/reduce": [{"py/function": "numpy.core.multiarray.scalar"}, {"py/tuple": [{"py/id": 2}, {"py/b64": "MICEtP9WFMA="}]}]}, {"py/reduce": [{"py/function": "numpy.core.multiarray.scalar"}, {"py/tuple": [{"py/id": 2}, {"py/b64": "mNvj1JXDEcA="}]}]}, {"py/reduce": [{"py/function": "numpy.core.multiarray.scalar"}, {"py/tuple": [{"py/id": 2}, {"py/b64": "olXcm7AGFMA="}]}]}, {"py/reduce": [{"py/function": "numpy.core.multiarray.scalar"}, {"py/tuple": [{"py/id": 2}, {"py/b64": "JGBprwY0FMA="}]}]}, {"py/reduce": [{"py/function": "numpy.core.multiarray.scalar"}, {"py/tuple": [{"py/id": 2}, {"py/b64": "wWzpp0YrFcA="}]}]}, {"py/reduce": [{"py/function": "numpy.core.multiarray.scalar"}, {"py/tuple": [{"py/id": 2}, {"py/b64": "7QHqFARaFMA="}]}]}, {"py/reduce": [{"py/function": "numpy.core.multiarray.scalar"}, {"py/tuple": [{"py/id": 2}, {"py/b64": "fXaAUO9GEsA="}]}]}, {"py/reduce": [{"py/function": "numpy.core.multiarray.scalar"}, {"py/tuple": [{"py/id": 2}, {"py/b64": "kPILEGBKEsA="}]}]}, {"py/reduce": [{"py/function": "numpy.core.multiarray.scalar"}, {"py/tuple": [{"py/id": 2}, {"py/b64": "06d95mRtEMA="}]}]}, {"py/reduce": [{"py/function": "numpy.core.multiarray.scalar"}, {"py/tuple": [{"py/id": 2}, {"py/b64": "vOuvcsExFsA="}]}]}, {"py/reduce": [{"py/function": "numpy.core.multiarray.scalar"}, {"py/tuple": [{"py/id": 2}, {"py/b64": "FY+mzGfhEsA="}]}]}, {"py/reduce": [{"py/function": "numpy.core.multiarray.scalar"}, {"py/tuple": [{"py/id": 2}, {"py/b64": "KgOc2YdGDsA="}]}]}, {"py/reduce": [{"py/function": "numpy.core.multiarray.scalar"}, {"py/tuple": [{"py/id": 2}, {"py/b64": "CxrenpDwEcA="}]}]}, {"py/reduce": [{"py/function": "numpy.core.multiarray.scalar"}, {"py/tuple": [{"py/id": 2}, {"py/b64": "mQU1UMryEsA="}]}]}, {"py/reduce": [{"py/function": "numpy.core.multiarray.scalar"}, {"py/tuple": [{"py/id": 2}, {"py/b64": "FnMwewvHEMA="}]}]}, {"py/reduce": [{"py/function": "numpy.core.multiarray.scalar"}, {"py/tuple": [{"py/id": 2}, {"py/b64": "wKmGSipbFcA="}]}]}, {"py/reduce": [{"py/function": "numpy.core.multiarray.scalar"}, {"py/tuple": [{"py/id": 2}, {"py/b64": "+lSuEc/CE8A="}]}]}, {"py/reduce": [{"py/function": "numpy.core.multiarray.scalar"}, {"py/tuple": [{"py/id": 2}, {"py/b64": "hGIKdZWZE8A="}]}]}, {"py/reduce": [{"py/function": "numpy.core.multiarray.scalar"}, {"py/tuple": [{"py/id": 2}, {"py/b64": "b1JY8+pqEsA="}]}]}, {"py/reduce": [{"py/function": "numpy.core.multiarray.scalar"}, {"py/tuple": [{"py/id": 2}, {"py/b64": "tQaiIE21E8A="}]}]}, {"py/reduce": [{"py/function": "numpy.core.multiarray.scalar"}, {"py/tuple": [{"py/id": 2}, {"py/b64": "q/ey4DOeEMA="}]}]}, {"py/reduce": [{"py/function": "numpy.core.multiarray.scalar"}, {"py/tuple": [{"py/id": 2}, {"py/b64": "zqfzS0EoE8A="}]}]}, {"py/reduce": [{"py/function": "numpy.core.multiarray.scalar"}, {"py/tuple": [{"py/id": 2}, {"py/b64": "TNtL/ASmEsA="}]}]}, {"py/reduce": [{"py/function": "numpy.core.multiarray.scalar"}, {"py/tuple": [{"py/id": 2}, {"py/b64": "dlAqoO6ZFcA="}]}]}, {"py/reduce": [{"py/function": "numpy.core.multiarray.scalar"}, {"py/tuple": [{"py/id": 2}, {"py/b64": "KQmCcXBiFcA="}]}]}, {"py/reduce": [{"py/function": "numpy.core.multiarray.scalar"}, {"py/tuple": [{"py/id": 2}, {"py/b64": "ocv+WleaFcA="}]}]}, {"py/reduce": [{"py/function": "numpy.core.multiarray.scalar"}, {"py/tuple": [{"py/id": 2}, {"py/b64": "7ap67jhgE8A="}]}]}, {"py/reduce": [{"py/function": "numpy.core.multiarray.scalar"}, {"py/tuple": [{"py/id": 2}, {"py/b64": "kRi0VmypFMA="}]}]}, {"py/reduce": [{"py/function": "numpy.core.multiarray.scalar"}, {"py/tuple": [{"py/id": 2}, {"py/b64": "wein5ID9DsA="}]}]}, {"py/reduce": [{"py/function": "numpy.core.multiarray.scalar"}, {"py/tuple": [{"py/id": 2}, {"py/b64": "e6mlLneFFMA="}]}]}, {"py/reduce": [{"py/function": "numpy.core.multiarray.scalar"}, {"py/tuple": [{"py/id": 2}, {"py/b64": "pPFD2iRbEsA="}]}]}, {"py/reduce": [{"py/function": "numpy.core.multiarray.scalar"}, {"py/tuple": [{"py/id": 2}, {"py/b64": "q+SCbp4qFMA="}]}]}, {"py/reduce": [{"py/function": "numpy.core.multiarray.scalar"}, {"py/tuple": [{"py/id": 2}, {"py/b64": "TJqrhc51EMA="}]}]}, {"py/reduce": [{"py/function": "numpy.core.multiarray.scalar"}, {"py/tuple": [{"py/id": 2}, {"py/b64": "Gme1vUSXE8A="}]}]}, {"py/reduce": [{"py/function": "numpy.core.multiarray.scalar"}, {"py/tuple": [{"py/id": 2}, {"py/b64": "UowwzA06FsA="}]}]}, {"py/reduce": [{"py/function": "numpy.core.multiarray.scalar"}, {"py/tuple": [{"py/id": 2}, {"py/b64": "gWRCp8cRE8A="}]}]}, {"py/reduce": [{"py/function": "numpy.core.multiarray.scalar"}, {"py/tuple": [{"py/id": 2}, {"py/b64": "CB+71eKGEMA="}]}]}, {"py/reduce": [{"py/function": "numpy.core.multiarray.scalar"}, {"py/tuple": [{"py/id": 2}, {"py/b64": "z7w8XPJpE8A="}]}]}, {"py/reduce": [{"py/function": "numpy.core.multiarray.scalar"}, {"py/tuple": [{"py/id": 2}, {"py/b64": "IYqE+BomE8A="}]}]}, {"py/reduce": [{"py/function": "numpy.core.multiarray.scalar"}, {"py/tuple": [{"py/id": 2}, {"py/b64": "ZKjpb8R5FcA="}]}]}, {"py/reduce": [{"py/function": "numpy.core.multiarray.scalar"}, {"py/tuple": [{"py/id": 2}, {"py/b64": "4SBfb4jvEsA="}]}]}, {"py/reduce": [{"py/function": "numpy.core.multiarray.scalar"}, {"py/tuple": [{"py/id": 2}, {"py/b64": "W9Tm0WTtFcA="}]}]}, {"py/reduce": [{"py/function": "numpy.core.multiarray.scalar"}, {"py/tuple": [{"py/id": 2}, {"py/b64": "+T8r0EriEcA="}]}]}, {"py/reduce": [{"py/function": "numpy.core.multiarray.scalar"}, {"py/tuple": [{"py/id": 2}, {"py/b64": "RUCDYpl2EsA="}]}]}, {"py/reduce": [{"py/function": "numpy.core.multiarray.scalar"}, {"py/tuple": [{"py/id": 2}, {"py/b64": "GOdyi1h6EcA="}]}]}, {"py/reduce": [{"py/function": "numpy.core.multiarray.scalar"}, {"py/tuple": [{"py/id": 2}, {"py/b64": "RNaSrmhBEcA="}]}]}, {"py/reduce": [{"py/function": "numpy.core.multiarray.scalar"}, {"py/tuple": [{"py/id": 2}, {"py/b64": "THLtcsRjEsA="}]}]}, {"py/reduce": [{"py/function": "numpy.core.multiarray.scalar"}, {"py/tuple": [{"py/id": 2}, {"py/b64": "r1KVwSs7FcA="}]}]}, {"py/reduce": [{"py/function": "numpy.core.multiarray.scalar"}, {"py/tuple": [{"py/id": 2}, {"py/b64": "0ey/6VeUFMA="}]}]}, {"py/reduce": [{"py/function": "numpy.core.multiarray.scalar"}, {"py/tuple": [{"py/id": 2}, {"py/b64": "HCYh/uOZFcA="}]}]}, {"py/reduce": [{"py/function": "numpy.core.multiarray.scalar"}, {"py/tuple": [{"py/id": 2}, {"py/b64": "01AoNMVuEcA="}]}]}, {"py/reduce": [{"py/function": "numpy.core.multiarray.scalar"}, {"py/tuple": [{"py/id": 2}, {"py/b64": "kr/tyFxBE8A="}]}]}, {"py/reduce": [{"py/function": "numpy.core.multiarray.scalar"}, {"py/tuple": [{"py/id": 2}, {"py/b64": "2KjbIramE8A="}]}]}, {"py/reduce": [{"py/function": "numpy.core.multiarray.scalar"}, {"py/tuple": [{"py/id": 2}, {"py/b64": "DT1gPDs/EcA="}]}]}, {"py/reduce": [{"py/function": "numpy.core.multiarray.scalar"}, {"py/tuple": [{"py/id": 2}, {"py/b64": "HGYjgjvUE8A="}]}]}, {"py/reduce": [{"py/function": "numpy.core.multiarray.scalar"}, {"py/tuple": [{"py/id": 2}, {"py/b64": "OvEU+DicEMA="}]}]}, {"py/reduce": [{"py/function": "numpy.core.multiarray.scalar"}, {"py/tuple": [{"py/id": 2}, {"py/b64": "zyH5YHkyEMA="}]}]}, {"py/reduce": [{"py/function": "numpy.core.multiarray.scalar"}, {"py/tuple": [{"py/id": 2}, {"py/b64": "pY9S7fcuFMA="}]}]}, {"py/reduce": [{"py/function": "numpy.core.multiarray.scalar"}, {"py/tuple": [{"py/id": 2}, {"py/b64": "bLnZAP/pE8A="}]}]}, {"py/reduce": [{"py/function": "numpy.core.multiarray.scalar"}, {"py/tuple": [{"py/id": 2}, {"py/b64": "NuIjuwYJF8A="}]}]}, {"py/reduce": [{"py/function": "numpy.core.multiarray.scalar"}, {"py/tuple": [{"py/id": 2}, {"py/b64": "GGHm8A8yEcA="}]}]}, {"py/reduce": [{"py/function": "numpy.core.multiarray.scalar"}, {"py/tuple": [{"py/id": 2}, {"py/b64": "RP4reGX3EMA="}]}]}, {"py/reduce": [{"py/function": "numpy.core.multiarray.scalar"}, {"py/tuple": [{"py/id": 2}, {"py/b64": "walPzsI2EcA="}]}]}, {"py/reduce": [{"py/function": "numpy.core.multiarray.scalar"}, {"py/tuple": [{"py/id": 2}, {"py/b64": "duIOoabuEsA="}]}]}, {"py/reduce": [{"py/function": "numpy.core.multiarray.scalar"}, {"py/tuple": [{"py/id": 2}, {"py/b64": "JYfZiFy3EMA="}]}]}, {"py/reduce": [{"py/function": "numpy.core.multiarray.scalar"}, {"py/tuple": [{"py/id": 2}, {"py/b64": "GKCKzFY0EcA="}]}]}, {"py/reduce": [{"py/function": "numpy.core.multiarray.scalar"}, {"py/tuple": [{"py/id": 2}, {"py/b64": "tIZ6C5aQEcA="}]}]}, {"py/reduce": [{"py/function": "numpy.core.multiarray.scalar"}, {"py/tuple": [{"py/id": 2}, {"py/b64": "iZBzwFA5EMA="}]}]}, {"py/reduce": [{"py/function": "numpy.core.multiarray.scalar"}, {"py/tuple": [{"py/id": 2}, {"py/b64": "26+pylz5D8A="}]}]}, {"py/reduce": [{"py/function": "numpy.core.multiarray.scalar"}, {"py/tuple": [{"py/id": 2}, {"py/b64": "b2pjjRV+E8A="}]}]}, {"py/reduce": [{"py/function": "numpy.core.multiarray.scalar"}, {"py/tuple": [{"py/id": 2}, {"py/b64": "BvwH9ePMDMA="}]}]}, {"py/reduce": [{"py/function": "numpy.core.multiarray.scalar"}, {"py/tuple": [{"py/id": 2}, {"py/b64": "qSgeDO9wEsA="}]}]}, {"py/reduce": [{"py/function": "numpy.core.multiarray.scalar"}, {"py/tuple": [{"py/id": 2}, {"py/b64": "oZZf3lfMEMA="}]}]}, {"py/reduce": [{"py/function": "numpy.core.multiarray.scalar"}, {"py/tuple": [{"py/id": 2}, {"py/b64": "+uTJ2RTFDcA="}]}]}, {"py/reduce": [{"py/function": "numpy.core.multiarray.scalar"}, {"py/tuple": [{"py/id": 2}, {"py/b64": "/WCTVuWYDsA="}]}]}, {"py/reduce": [{"py/function": "numpy.core.multiarray.scalar"}, {"py/tuple": [{"py/id": 2}, {"py/b64": "BMqVHyfeDMA="}]}]}, {"py/reduce": [{"py/function": "numpy.core.multiarray.scalar"}, {"py/tuple": [{"py/id": 2}, {"py/b64": "hEq6yUpJEcA="}]}]}, {"py/reduce": [{"py/function": "numpy.core.multiarray.scalar"}, {"py/tuple": [{"py/id": 2}, {"py/b64": "hggkwzdqEcA="}]}]}, {"py/reduce": [{"py/function": "numpy.core.multiarray.scalar"}, {"py/tuple": [{"py/id": 2}, {"py/b64": "RU8hIPZMD8A="}]}]}, {"py/reduce": [{"py/function": "numpy.core.multiarray.scalar"}, {"py/tuple": [{"py/id": 2}, {"py/b64": "HxQWtqycDsA="}]}]}, {"py/reduce": [{"py/function": "numpy.core.multiarray.scalar"}, {"py/tuple": [{"py/id": 2}, {"py/b64": "816gDPodEMA="}]}]}, {"py/reduce": [{"py/function": "numpy.core.multiarray.scalar"}, {"py/tuple": [{"py/id": 2}, {"py/b64": "GFmXk+ZgDsA="}]}]}, {"py/reduce": [{"py/function": "numpy.core.multiarray.scalar"}, {"py/tuple": [{"py/id": 2}, {"py/b64": "89K9SEOKDMA="}]}]}, {"py/reduce": [{"py/function": "numpy.core.multiarray.scalar"}, {"py/tuple": [{"py/id": 2}, {"py/b64": "m5qWYTwJEsA="}]}]}, {"py/reduce": [{"py/function": "numpy.core.multiarray.scalar"}, {"py/tuple": [{"py/id": 2}, {"py/b64": "pK2yvUboCsA="}]}]}, {"py/reduce": [{"py/function": "numpy.core.multiarray.scalar"}, {"py/tuple": [{"py/id": 2}, {"py/b64": "Tbdz4Bw7EMA="}]}]}, {"py/reduce": [{"py/function": "numpy.core.multiarray.scalar"}, {"py/tuple": [{"py/id": 2}, {"py/b64": "zYEVFWrQEMA="}]}]}, {"py/reduce": [{"py/function": "numpy.core.multiarray.scalar"}, {"py/tuple": [{"py/id": 2}, {"py/b64": "ZYZrLOnPDsA="}]}]}, {"py/reduce": [{"py/function": "numpy.core.multiarray.scalar"}, {"py/tuple": [{"py/id": 2}, {"py/b64": "rBn/bDDzEMA="}]}]}, {"py/reduce": [{"py/function": "numpy.core.multiarray.scalar"}, {"py/tuple": [{"py/id": 2}, {"py/b64": "s6PJDEZWEsA="}]}]}, {"py/reduce": [{"py/function": "numpy.core.multiarray.scalar"}, {"py/tuple": [{"py/id": 2}, {"py/b64": "ljVpJT33DsA="}]}]}, {"py/reduce": [{"py/function": "numpy.core.multiarray.scalar"}, {"py/tuple": [{"py/id": 2}, {"py/b64": "swOfXC/RCcA="}]}]}, {"py/reduce": [{"py/function": "numpy.core.multiarray.scalar"}, {"py/tuple": [{"py/id": 2}, {"py/b64": "PcnBRmT2DsA="}]}]}, {"py/reduce": [{"py/function": "numpy.core.multiarray.scalar"}, {"py/tuple": [{"py/id": 2}, {"py/b64": "QA66Tc8LEcA="}]}]}, {"py/reduce": [{"py/function": "numpy.core.multiarray.scalar"}, {"py/tuple": [{"py/id": 2}, {"py/b64": "jllVNeqvD8A="}]}]}, {"py/reduce": [{"py/function": "numpy.core.multiarray.scalar"}, {"py/tuple": [{"py/id": 2}, {"py/b64": "ziNGHFo6EcA="}]}]}, {"py/reduce": [{"py/function": "numpy.core.multiarray.scalar"}, {"py/tuple": [{"py/id": 2}, {"py/b64": "zXcpf9A6DcA="}]}]}, {"py/reduce": [{"py/function": "numpy.core.multiarray.scalar"}, {"py/tuple": [{"py/id": 2}, {"py/b64": "Wzzpui2WDMA="}]}]}, {"py/reduce": [{"py/function": "numpy.core.multiarray.scalar"}, {"py/tuple": [{"py/id": 2}, {"py/b64": "qCGSXjjJEcA="}]}]}, {"py/reduce": [{"py/function": "numpy.core.multiarray.scalar"}, {"py/tuple": [{"py/id": 2}, {"py/b64": "YMVZ5nJwDMA="}]}]}, {"py/reduce": [{"py/function": "numpy.core.multiarray.scalar"}, {"py/tuple": [{"py/id": 2}, {"py/b64": "9Lyz9mq6DsA="}]}]}, {"py/reduce": [{"py/function": "numpy.core.multiarray.scalar"}, {"py/tuple": [{"py/id": 2}, {"py/b64": "PJAdC+/AEcA="}]}]}, {"py/reduce": [{"py/function": "numpy.core.multiarray.scalar"}, {"py/tuple": [{"py/id": 2}, {"py/b64": "JStEyXN6DcA="}]}]}, {"py/reduce": [{"py/function": "numpy.core.multiarray.scalar"}, {"py/tuple": [{"py/id": 2}, {"py/b64": "MwqjrMrnDcA="}]}]}, {"py/reduce": [{"py/function": "numpy.core.multiarray.scalar"}, {"py/tuple": [{"py/id": 2}, {"py/b64": "YR+K/0F9EMA="}]}]}, {"py/reduce": [{"py/function": "numpy.core.multiarray.scalar"}, {"py/tuple": [{"py/id": 2}, {"py/b64": "H0fHaPpxDsA="}]}]}, {"py/reduce": [{"py/function": "numpy.core.multiarray.scalar"}, {"py/tuple": [{"py/id": 2}, {"py/b64": "SzSvW55yEMA="}]}]}, {"py/reduce": [{"py/function": "numpy.core.multiarray.scalar"}, {"py/tuple": [{"py/id": 2}, {"py/b64": "03D3rbRzEMA="}]}]}, {"py/reduce": [{"py/function": "numpy.core.multiarray.scalar"}, {"py/tuple": [{"py/id": 2}, {"py/b64": "/FZh1VITEMA="}]}]}, {"py/reduce": [{"py/function": "numpy.core.multiarray.scalar"}, {"py/tuple": [{"py/id": 2}, {"py/b64": "uP0+AYn3DMA="}]}]}, {"py/reduce": [{"py/function": "numpy.core.multiarray.scalar"}, {"py/tuple": [{"py/id": 2}, {"py/b64": "TUxvKUa9DsA="}]}]}, {"py/reduce": [{"py/function": "numpy.core.multiarray.scalar"}, {"py/tuple": [{"py/id": 2}, {"py/b64": "rt/vlbWZEMA="}]}]}, {"py/reduce": [{"py/function": "numpy.core.multiarray.scalar"}, {"py/tuple": [{"py/id": 2}, {"py/b64": "nDJXYNDMEcA="}]}]}, {"py/reduce": [{"py/function": "numpy.core.multiarray.scalar"}, {"py/tuple": [{"py/id": 2}, {"py/b64": "tLj/hUiYEMA="}]}]}, {"py/reduce": [{"py/function": "numpy.core.multiarray.scalar"}, {"py/tuple": [{"py/id": 2}, {"py/b64": "Q/qAbESXDcA="}]}]}, {"py/reduce": [{"py/function": "numpy.core.multiarray.scalar"}, {"py/tuple": [{"py/id": 2}, {"py/b64": "QRkIzDPoDcA="}]}]}, {"py/reduce": [{"py/function": "numpy.core.multiarray.scalar"}, {"py/tuple": [{"py/id": 2}, {"py/b64": "v3LAeZ2tDsA="}]}]}, {"py/reduce": [{"py/function": "numpy.core.multiarray.scalar"}, {"py/tuple": [{"py/id": 2}, {"py/b64": "t0Vo8f16DMA="}]}]}, {"py/reduce": [{"py/function": "numpy.core.multiarray.scalar"}, {"py/tuple": [{"py/id": 2}, {"py/b64": "uILkXvE1C8A="}]}]}, {"py/reduce": [{"py/function": "numpy.core.multiarray.scalar"}, {"py/tuple": [{"py/id": 2}, {"py/b64": "7g6Sz6r/DMA="}]}]}, {"py/reduce": [{"py/function": "numpy.core.multiarray.scalar"}, {"py/tuple": [{"py/id": 2}, {"py/b64": "gfWVN77zDcA="}]}]}, {"py/reduce": [{"py/function": "numpy.core.multiarray.scalar"}, {"py/tuple": [{"py/id": 2}, {"py/b64": "dLgG7rpeDsA="}]}]}, {"py/reduce": [{"py/function": "numpy.core.multiarray.scalar"}, {"py/tuple": [{"py/id": 2}, {"py/b64": "xXH5JvW2DsA="}]}]}, {"py/reduce": [{"py/function": "numpy.core.multiarray.scalar"}, {"py/tuple": [{"py/id": 2}, {"py/b64": "Ur48bgICD8A="}]}]}, {"py/reduce": [{"py/function": "numpy.core.multiarray.scalar"}, {"py/tuple": [{"py/id": 2}, {"py/b64": "3JzBpjSIDcA="}]}]}, {"py/reduce": [{"py/function": "numpy.core.multiarray.scalar"}, {"py/tuple": [{"py/id": 2}, {"py/b64": "0u7XM14RD8A="}]}]}, {"py/reduce": [{"py/function": "numpy.core.multiarray.scalar"}, {"py/tuple": [{"py/id": 2}, {"py/b64": "TAKgG4gfDMA="}]}]}, {"py/reduce": [{"py/function": "numpy.core.multiarray.scalar"}, {"py/tuple": [{"py/id": 2}, {"py/b64": "w8sLXIUcD8A="}]}]}, {"py/reduce": [{"py/function": "numpy.core.multiarray.scalar"}, {"py/tuple": [{"py/id": 2}, {"py/b64": "Y7s0KD7hDcA="}]}]}, {"py/reduce": [{"py/function": "numpy.core.multiarray.scalar"}, {"py/tuple": [{"py/id": 2}, {"py/b64": "psDiq5O0C8A="}]}]}, {"py/reduce": [{"py/function": "numpy.core.multiarray.scalar"}, {"py/tuple": [{"py/id": 2}, {"py/b64": "LzOievB1C8A="}]}]}, {"py/reduce": [{"py/function": "numpy.core.multiarray.scalar"}, {"py/tuple": [{"py/id": 2}, {"py/b64": "t5tAyxTcDMA="}]}]}, {"py/reduce": [{"py/function": "numpy.core.multiarray.scalar"}, {"py/tuple": [{"py/id": 2}, {"py/b64": "FlDICL1gC8A="}]}]}, {"py/reduce": [{"py/function": "numpy.core.multiarray.scalar"}, {"py/tuple": [{"py/id": 2}, {"py/b64": "KF51scSLDsA="}]}]}, {"py/reduce": [{"py/function": "numpy.core.multiarray.scalar"}, {"py/tuple": [{"py/id": 2}, {"py/b64": "QLvfMv4RDMA="}]}]}, {"py/reduce": [{"py/function": "numpy.core.multiarray.scalar"}, {"py/tuple": [{"py/id": 2}, {"py/b64": "zAg3eA32DMA="}]}]}, {"py/reduce": [{"py/function": "numpy.core.multiarray.scalar"}, {"py/tuple": [{"py/id": 2}, {"py/b64": "REHcYvYCDcA="}]}]}, {"py/reduce": [{"py/function": "numpy.core.multiarray.scalar"}, {"py/tuple": [{"py/id": 2}, {"py/b64": "5ae3rgE4DcA="}]}]}, {"py/reduce": [{"py/function": "numpy.core.multiarray.scalar"}, {"py/tuple": [{"py/id": 2}, {"py/b64": "YnumI8hLEsA="}]}]}, {"py/reduce": [{"py/function": "numpy.core.multiarray.scalar"}, {"py/tuple": [{"py/id": 2}, {"py/b64": "sREU7vPdDcA="}]}]}, {"py/reduce": [{"py/function": "numpy.core.multiarray.scalar"}, {"py/tuple": [{"py/id": 2}, {"py/b64": "iUILDAIhD8A="}]}]}, {"py/reduce": [{"py/function": "numpy.core.multiarray.scalar"}, {"py/tuple": [{"py/id": 2}, {"py/b64": "LP2q8wGzDsA="}]}]}, {"py/reduce": [{"py/function": "numpy.core.multiarray.scalar"}, {"py/tuple": [{"py/id": 2}, {"py/b64": "wRSdv7O/D8A="}]}]}, {"py/reduce": [{"py/function": "numpy.core.multiarray.scalar"}, {"py/tuple": [{"py/id": 2}, {"py/b64": "2rTkPExkDcA="}]}]}, {"py/reduce": [{"py/function": "numpy.core.multiarray.scalar"}, {"py/tuple": [{"py/id": 2}, {"py/b64": "W/9BtfvoDMA="}]}]}, {"py/reduce": [{"py/function": "numpy.core.multiarray.scalar"}, {"py/tuple": [{"py/id": 2}, {"py/b64": "G1ONGUKxDMA="}]}]}, {"py/reduce": [{"py/function": "numpy.core.multiarray.scalar"}, {"py/tuple": [{"py/id": 2}, {"py/b64": "WPSXg8HGDcA="}]}]}, {"py/reduce": [{"py/function": "numpy.core.multiarray.scalar"}, {"py/tuple": [{"py/id": 2}, {"py/b64": "uGuu7j6cEMA="}]}]}, {"py/reduce": [{"py/function": "numpy.core.multiarray.scalar"}, {"py/tuple": [{"py/id": 2}, {"py/b64": "rA7sXpufDcA="}]}]}, {"py/reduce": [{"py/function": "numpy.core.multiarray.scalar"}, {"py/tuple": [{"py/id": 2}, {"py/b64": "brJHgZfHCsA="}]}]}, {"py/reduce": [{"py/function": "numpy.core.multiarray.scalar"}, {"py/tuple": [{"py/id": 2}, {"py/b64": "CE/9Dl8mDcA="}]}]}, {"py/reduce": [{"py/function": "numpy.core.multiarray.scalar"}, {"py/tuple": [{"py/id": 2}, {"py/b64": "1kb0i789C8A="}]}]}, {"py/reduce": [{"py/function": "numpy.core.multiarray.scalar"}, {"py/tuple": [{"py/id": 2}, {"py/b64": "JZPV4KzmDsA="}]}]}, {"py/reduce": [{"py/function": "numpy.core.multiarray.scalar"}, {"py/tuple": [{"py/id": 2}, {"py/b64": "5djjz25VDMA="}]}]}, {"py/reduce": [{"py/function": "numpy.core.multiarray.scalar"}, {"py/tuple": [{"py/id": 2}, {"py/b64": "oSACZtKdDsA="}]}]}, {"py/reduce": [{"py/function": "numpy.core.multiarray.scalar"}, {"py/tuple": [{"py/id": 2}, {"py/b64": "T+eXIErNCcA="}]}]}, {"py/reduce": [{"py/function": "numpy.core.multiarray.scalar"}, {"py/tuple": [{"py/id": 2}, {"py/b64": "PfjWbCF3EMA="}]}]}, {"py/reduce": [{"py/function": "numpy.core.multiarray.scalar"}, {"py/tuple": [{"py/id": 2}, {"py/b64": "WM9NO5a5DsA="}]}]}, {"py/reduce": [{"py/function": "numpy.core.multiarray.scalar"}, {"py/tuple": [{"py/id": 2}, {"py/b64": "6DShopZID8A="}]}]}, {"py/reduce": [{"py/function": "numpy.core.multiarray.scalar"}, {"py/tuple": [{"py/id": 2}, {"py/b64": "juz9f89MC8A="}]}]}, {"py/reduce": [{"py/function": "numpy.core.multiarray.scalar"}, {"py/tuple": [{"py/id": 2}, {"py/b64": "f167eKs1C8A="}]}]}, {"py/reduce": [{"py/function": "numpy.core.multiarray.scalar"}, {"py/tuple": [{"py/id": 2}, {"py/b64": "yS/hgpTtCsA="}]}]}, {"py/reduce": [{"py/function": "numpy.core.multiarray.scalar"}, {"py/tuple": [{"py/id": 2}, {"py/b64": "Wh4CvIPBDMA="}]}]}, {"py/reduce": [{"py/function": "numpy.core.multiarray.scalar"}, {"py/tuple": [{"py/id": 2}, {"py/b64": "IxuwyvyMC8A="}]}]}, {"py/reduce": [{"py/function": "numpy.core.multiarray.scalar"}, {"py/tuple": [{"py/id": 2}, {"py/b64": "fV9tbLBoD8A="}]}]}, {"py/reduce": [{"py/function": "numpy.core.multiarray.scalar"}, {"py/tuple": [{"py/id": 2}, {"py/b64": "U929HXBlEMA="}]}]}, {"py/reduce": [{"py/function": "numpy.core.multiarray.scalar"}, {"py/tuple": [{"py/id": 2}, {"py/b64": "HdjUFgAED8A="}]}]}, {"py/reduce": [{"py/function": "numpy.core.multiarray.scalar"}, {"py/tuple": [{"py/id": 2}, {"py/b64": "P6YYigTZBcA="}]}]}, {"py/reduce": [{"py/function": "numpy.core.multiarray.scalar"}, {"py/tuple": [{"py/id": 2}, {"py/b64": "s5erFHYZC8A="}]}]}, {"py/reduce": [{"py/function": "numpy.core.multiarray.scalar"}, {"py/tuple": [{"py/id": 2}, {"py/b64": "u3V8h1hzDMA="}]}]}, {"py/reduce": [{"py/function": "numpy.core.multiarray.scalar"}, {"py/tuple": [{"py/id": 2}, {"py/b64": "7SkDtwI2EMA="}]}]}, {"py/reduce": [{"py/function": "numpy.core.multiarray.scalar"}, {"py/tuple": [{"py/id": 2}, {"py/b64": "hXVjoYYOCcA="}]}]}, {"py/reduce": [{"py/function": "numpy.core.multiarray.scalar"}, {"py/tuple": [{"py/id": 2}, {"py/b64": "ZYmPOqFxDcA="}]}]}, {"py/reduce": [{"py/function": "numpy.core.multiarray.scalar"}, {"py/tuple": [{"py/id": 2}, {"py/b64": "kUf0wxdrC8A="}]}]}, {"py/reduce": [{"py/function": "numpy.core.multiarray.scalar"}, {"py/tuple": [{"py/id": 2}, {"py/b64": "KIzZu4jBCMA="}]}]}, {"py/reduce": [{"py/function": "numpy.core.multiarray.scalar"}, {"py/tuple": [{"py/id": 2}, {"py/b64": "OrJyN6hiEMA="}]}]}, {"py/reduce": [{"py/function": "numpy.core.multiarray.scalar"}, {"py/tuple": [{"py/id": 2}, {"py/b64": "4cbbnokGB8A="}]}]}, {"py/reduce": [{"py/function": "numpy.core.multiarray.scalar"}, {"py/tuple": [{"py/id": 2}, {"py/b64": "NANTsjIrDcA="}]}]}, {"py/reduce": [{"py/function": "numpy.core.multiarray.scalar"}, {"py/tuple": [{"py/id": 2}, {"py/b64": "t0lALyMPDMA="}]}]}, {"py/reduce": [{"py/function": "numpy.core.multiarray.scalar"}, {"py/tuple": [{"py/id": 2}, {"py/b64": "6GbJbxovDsA="}]}]}, {"py/reduce": [{"py/function": "numpy.core.multiarray.scalar"}, {"py/tuple": [{"py/id": 2}, {"py/b64": "c/MMDncyC8A="}]}]}, {"py/reduce": [{"py/function": "numpy.core.multiarray.scalar"}, {"py/tuple": [{"py/id": 2}, {"py/b64": "QYR0PR8ZDMA="}]}]}, {"py/reduce": [{"py/function": "numpy.core.multiarray.scalar"}, {"py/tuple": [{"py/id": 2}, {"py/b64": "LB8Ivye3DsA="}]}]}, {"py/reduce": [{"py/function": "numpy.core.multiarray.scalar"}, {"py/tuple": [{"py/id": 2}, {"py/b64": "gPr9/J4SCcA="}]}]}, {"py/reduce": [{"py/function": "numpy.core.multiarray.scalar"}, {"py/tuple": [{"py/id": 2}, {"py/b64": "cPf8UFAcEMA="}]}]}, {"py/reduce": [{"py/function": "numpy.core.multiarray.scalar"}, {"py/tuple": [{"py/id": 2}, {"py/b64": "8V8+I0sZCsA="}]}]}, {"py/reduce": [{"py/function": "numpy.core.multiarray.scalar"}, {"py/tuple": [{"py/id": 2}, {"py/b64": "EbRYml8hDsA="}]}]}, {"py/reduce": [{"py/function": "numpy.core.multiarray.scalar"}, {"py/tuple": [{"py/id": 2}, {"py/b64": "uAlyiiFWCMA="}]}]}, {"py/reduce": [{"py/function": "numpy.core.multiarray.scalar"}, {"py/tuple": [{"py/id": 2}, {"py/b64": "3WvLkWFbDsA="}]}]}, {"py/reduce": [{"py/function": "numpy.core.multiarray.scalar"}, {"py/tuple": [{"py/id": 2}, {"py/b64": "7J4elgJwCcA="}]}]}, {"py/reduce": [{"py/function": "numpy.core.multiarray.scalar"}, {"py/tuple": [{"py/id": 2}, {"py/b64": "l9f6c+8fDMA="}]}]}, {"py/reduce": [{"py/function": "numpy.core.multiarray.scalar"}, {"py/tuple": [{"py/id": 2}, {"py/b64": "Wth2l9PIBsA="}]}]}, {"py/reduce": [{"py/function": "numpy.core.multiarray.scalar"}, {"py/tuple": [{"py/id": 2}, {"py/b64": "qEMYb0DnDsA="}]}]}, {"py/reduce": [{"py/function": "numpy.core.multiarray.scalar"}, {"py/tuple": [{"py/id": 2}, {"py/b64": "SpvxlNA+D8A="}]}]}, {"py/reduce": [{"py/function": "numpy.core.multiarray.scalar"}, {"py/tuple": [{"py/id": 2}, {"py/b64": "wZjjsQrqDMA="}]}]}, {"py/reduce": [{"py/function": "numpy.core.multiarray.scalar"}, {"py/tuple": [{"py/id": 2}, {"py/b64": "ra0/cFM1CsA="}]}]}, {"py/reduce": [{"py/function": "numpy.core.multiarray.scalar"}, {"py/tuple": [{"py/id": 2}, {"py/b64": "TsP1rOz3CMA="}]}]}, {"py/reduce": [{"py/function": "numpy.core.multiarray.scalar"}, {"py/tuple": [{"py/id": 2}, {"py/b64": "vAybopXmC8A="}]}]}, {"py/reduce": [{"py/function": "numpy.core.multiarray.scalar"}, {"py/tuple": [{"py/id": 2}, {"py/b64": "ahhS5FbeDcA="}]}]}, {"py/reduce": [{"py/function": "numpy.core.multiarray.scalar"}, {"py/tuple": [{"py/id": 2}, {"py/b64": "IORebd5ADcA="}]}]}, {"py/reduce": [{"py/function": "numpy.core.multiarray.scalar"}, {"py/tuple": [{"py/id": 2}, {"py/b64": "GzgNgj7lBcA="}]}]}, {"py/reduce": [{"py/function": "numpy.core.multiarray.scalar"}, {"py/tuple": [{"py/id": 2}, {"py/b64": "8ueI0/FmDMA="}]}]}, {"py/reduce": [{"py/function": "numpy.core.multiarray.scalar"}, {"py/tuple": [{"py/id": 2}, {"py/b64": "UlbepSe0DcA="}]}]}, {"py/reduce": [{"py/function": "numpy.core.multiarray.scalar"}, {"py/tuple": [{"py/id": 2}, {"py/b64": "8YqIlFg1DcA="}]}]}, {"py/reduce": [{"py/function": "numpy.core.multiarray.scalar"}, {"py/tuple": [{"py/id": 2}, {"py/b64": "4YttdGIsCcA="}]}]}, {"py/reduce": [{"py/function": "numpy.core.multiarray.scalar"}, {"py/tuple": [{"py/id": 2}, {"py/b64": "MqzbRjxFCsA="}]}]}, {"py/reduce": [{"py/function": "numpy.core.multiarray.scalar"}, {"py/tuple": [{"py/id": 2}, {"py/b64": "7KC9BT98DMA="}]}]}, {"py/reduce": [{"py/function": "numpy.core.multiarray.scalar"}, {"py/tuple": [{"py/id": 2}, {"py/b64": "mteSg3oNDcA="}]}]}, {"py/reduce": [{"py/function": "numpy.core.multiarray.scalar"}, {"py/tuple": [{"py/id": 2}, {"py/b64": "FAcM/pp7CsA="}]}]}, {"py/reduce": [{"py/function": "numpy.core.multiarray.scalar"}, {"py/tuple": [{"py/id": 2}, {"py/b64": "l7eCT9bvC8A="}]}]}, {"py/reduce": [{"py/function": "numpy.core.multiarray.scalar"}, {"py/tuple": [{"py/id": 2}, {"py/b64": "Pe51Rd5oD8A="}]}]}, {"py/reduce": [{"py/function": "numpy.core.multiarray.scalar"}, {"py/tuple": [{"py/id": 2}, {"py/b64": "iZF12dzHDsA="}]}]}, {"py/reduce": [{"py/function": "numpy.core.multiarray.scalar"}, {"py/tuple": [{"py/id": 2}, {"py/b64": "yrQQqIlFDcA="}]}]}, {"py/reduce": [{"py/function": "numpy.core.multiarray.scalar"}, {"py/tuple": [{"py/id": 2}, {"py/b64": "3NPyFEdhDcA="}]}]}, {"py/reduce": [{"py/function": "numpy.core.multiarray.scalar"}, {"py/tuple": [{"py/id": 2}, {"py/b64": "iiwLcq2DC8A="}]}]}, {"py/reduce": [{"py/function": "numpy.core.multiarray.scalar"}, {"py/tuple": [{"py/id": 2}, {"py/b64": "CrfiGwEgEcA="}]}]}, {"py/reduce": [{"py/function": "numpy.core.multiarray.scalar"}, {"py/tuple": [{"py/id": 2}, {"py/b64": "QGxzMnIBD8A="}]}]}, {"py/reduce": [{"py/function": "numpy.core.multiarray.scalar"}, {"py/tuple": [{"py/id": 2}, {"py/b64": "Sd/PJBmdDsA="}]}]}, {"py/reduce": [{"py/function": "numpy.core.multiarray.scalar"}, {"py/tuple": [{"py/id": 2}, {"py/b64": "xYIras+vCsA="}]}]}, {"py/reduce": [{"py/function": "numpy.core.multiarray.scalar"}, {"py/tuple": [{"py/id": 2}, {"py/b64": "/LBrjYaHDMA="}]}]}, {"py/reduce": [{"py/function": "numpy.core.multiarray.scalar"}, {"py/tuple": [{"py/id": 2}, {"py/b64": "9xfGbi5VDsA="}]}]}, {"py/reduce": [{"py/function": "numpy.core.multiarray.scalar"}, {"py/tuple": [{"py/id": 2}, {"py/b64": "RRe6jbGmD8A="}]}]}, {"py/reduce": [{"py/function": "numpy.core.multiarray.scalar"}, {"py/tuple": [{"py/id": 2}, {"py/b64": "WOZEX054DMA="}]}]}, {"py/reduce": [{"py/function": "numpy.core.multiarray.scalar"}, {"py/tuple": [{"py/id": 2}, {"py/b64": "/0YqqcB2EMA="}]}]}, {"py/reduce": [{"py/function": "numpy.core.multiarray.scalar"}, {"py/tuple": [{"py/id": 2}, {"py/b64": "mUIaHc1sEMA="}]}]}, {"py/reduce": [{"py/function": "numpy.core.multiarray.scalar"}, {"py/tuple": [{"py/id": 2}, {"py/b64": "w0lmDM7QC8A="}]}]}, {"py/reduce": [{"py/function": "numpy.core.multiarray.scalar"}, {"py/tuple": [{"py/id": 2}, {"py/b64": "+8KoMVCTB8A="}]}]}, {"py/reduce": [{"py/function": "numpy.core.multiarray.scalar"}, {"py/tuple": [{"py/id": 2}, {"py/b64": "nfpIZj6jCsA="}]}]}, {"py/reduce": [{"py/function": "numpy.core.multiarray.scalar"}, {"py/tuple": [{"py/id": 2}, {"py/b64": "G5rRxH4DC8A="}]}]}, {"py/reduce": [{"py/function": "numpy.core.multiarray.scalar"}, {"py/tuple": [{"py/id": 2}, {"py/b64": "JIsTnIcCDMA="}]}]}, {"py/reduce": [{"py/function": "numpy.core.multiarray.scalar"}, {"py/tuple": [{"py/id": 2}, {"py/b64": "VFTKgVRzDcA="}]}]}, {"py/reduce": [{"py/function": "numpy.core.multiarray.scalar"}, {"py/tuple": [{"py/id": 2}, {"py/b64": "N54yAruACMA="}]}]}, {"py/reduce": [{"py/function": "numpy.core.multiarray.scalar"}, {"py/tuple": [{"py/id": 2}, {"py/b64": "eJ8R9ZrsCcA="}]}]}, {"py/reduce": [{"py/function": "numpy.core.multiarray.scalar"}, {"py/tuple": [{"py/id": 2}, {"py/b64": "PFAoKfHiC8A="}]}]}, {"py/reduce": [{"py/function": "numpy.core.multiarray.scalar"}, {"py/tuple": [{"py/id": 2}, {"py/b64": "gync0AxqDsA="}]}]}, {"py/reduce": [{"py/function": "numpy.core.multiarray.scalar"}, {"py/tuple": [{"py/id": 2}, {"py/b64": "o+z1gydyDMA="}]}]}, {"py/reduce": [{"py/function": "numpy.core.multiarray.scalar"}, {"py/tuple": [{"py/id": 2}, {"py/b64": "bzsbdMxpDMA="}]}]}, {"py/reduce": [{"py/function": "numpy.core.multiarray.scalar"}, {"py/tuple": [{"py/id": 2}, {"py/b64": "Xy0fVBj7CsA="}]}]}, {"py/reduce": [{"py/function": "numpy.core.multiarray.scalar"}, {"py/tuple": [{"py/id": 2}, {"py/b64": "U1X/XACYD8A="}]}]}, {"py/reduce": [{"py/function": "numpy.core.multiarray.scalar"}, {"py/tuple": [{"py/id": 2}, {"py/b64": "Nkkc5xpFCsA="}]}]}, {"py/reduce": [{"py/function": "numpy.core.multiarray.scalar"}, {"py/tuple": [{"py/id": 2}, {"py/b64": "xsUd2VrECcA="}]}]}, {"py/reduce": [{"py/function": "numpy.core.multiarray.scalar"}, {"py/tuple": [{"py/id": 2}, {"py/b64": "3+sIbOWsCcA="}]}]}, {"py/reduce": [{"py/function": "numpy.core.multiarray.scalar"}, {"py/tuple": [{"py/id": 2}, {"py/b64": "39EAoiBiCcA="}]}]}, {"py/reduce": [{"py/function": "numpy.core.multiarray.scalar"}, {"py/tuple": [{"py/id": 2}, {"py/b64": "4+SC/ANFCMA="}]}]}, {"py/reduce": [{"py/function": "numpy.core.multiarray.scalar"}, {"py/tuple": [{"py/id": 2}, {"py/b64": "SNORKWmKC8A="}]}]}, {"py/reduce": [{"py/function": "numpy.core.multiarray.scalar"}, {"py/tuple": [{"py/id": 2}, {"py/b64": "6dWorHvUC8A="}]}]}, {"py/reduce": [{"py/function": "numpy.core.multiarray.scalar"}, {"py/tuple": [{"py/id": 2}, {"py/b64": "5PNrQQm8CsA="}]}]}, {"py/reduce": [{"py/function": "numpy.core.multiarray.scalar"}, {"py/tuple": [{"py/id": 2}, {"py/b64": "xZMeHSuXDsA="}]}]}, {"py/reduce": [{"py/function": "numpy.core.multiarray.scalar"}, {"py/tuple": [{"py/id": 2}, {"py/b64": "ID+nByXpCcA="}]}]}, {"py/reduce": [{"py/function": "numpy.core.multiarray.scalar"}, {"py/tuple": [{"py/id": 2}, {"py/b64": "Jd92lGcPD8A="}]}]}, {"py/reduce": [{"py/function": "numpy.core.multiarray.scalar"}, {"py/tuple": [{"py/id": 2}, {"py/b64": "LwH5B12eCsA="}]}]}, {"py/reduce": [{"py/function": "numpy.core.multiarray.scalar"}, {"py/tuple": [{"py/id": 2}, {"py/b64": "hEUFoFerD8A="}]}]}, {"py/reduce": [{"py/function": "numpy.core.multiarray.scalar"}, {"py/tuple": [{"py/id": 2}, {"py/b64": "VEG7qMJZD8A="}]}]}, {"py/reduce": [{"py/function": "numpy.core.multiarray.scalar"}, {"py/tuple": [{"py/id": 2}, {"py/b64": "pLpGSm01DcA="}]}]}, {"py/reduce": [{"py/function": "numpy.core.multiarray.scalar"}, {"py/tuple": [{"py/id": 2}, {"py/b64": "mxixgFLfD8A="}]}]}]}